{
  "droneCount": 200,
  "steps": [
    {
      "type": "formation",
      "formation": "circle",
      "motion": "smooth",
      "params": {
        "radius": 150,
        "y": 100,
        "variation": 10
      },
      "color": "#00ff00",
      "holdDuration": 2.0
    },
    {
      "type": "formation",
      "formation": "grid",
      "motion": "strobe",
      "params": {
        "rows": 10,
        "spacing": 20,
        "y": 125,
        "variation": 5
      },
      "color": "#ff00ff",
      "holdDuration": 2.5
    },
    {
      "type": "formation",
      "formation": "wave",
      "motion": "wave",
      "params": {
        "amplitude": 60,
        "frequency": 0.04,
        "y": 100,
        "spacing": 15
      },
      "color": "#00ffff",
      "holdDuration": 3.0
    },
    {
      "type": "formation",
      "formation": "line",
      "motion": "swing",
      "params": {
        "spacing": 15,
        "y": 80
      },
      "color": "#ffaa00",
      "holdDuration": 2.0
    },
    {
      "type": "formation",
      "formation": "grid",
      "motion": "fast",
      "params": {
        "rows": 14,
        "spacing": 15,
        "y": 0
      },
      "color": "#ffffff",
      "holdDuration": 5.0
    }
  ]
}
